frisbo/__init__.py
frisbo/client.py
frisbo/exceptions.py
frisbo/models.py
frisbo/types.py
frisbo/resources/__init__.py
frisbo/resources/auth.py
frisbo/resources/base.py
frisbo/resources/inbound.py
frisbo/resources/invoices.py
frisbo/resources/orders.py
frisbo/resources/organizations.py
frisbo/resources/products.py
frisbo-0.1.2.dist-info/METADATA
frisbo-0.1.2.dist-info/WHEEL
frisbo-0.1.2.dist-info/RECORD
