Metadata-Version: 2.4
Name: frisbo
Version: 0.1.2
Summary: Python SDK for the Frisbo API
Project-URL: Homepage, https://github.com/yegorov-p/frisbo
Project-URL: Documentation, https://developers.frisbo.ro/
Project-URL: Repository, https://github.com/yegorov-p/frisbo
Project-URL: Issues, https://github.com/yegorov-p/frisbo/issues
Author-email: Pasha Yegorov <yegorov.p@gmail.com>
License: MIT
Keywords: api,ecommerce,frisbo,fulfillment,sdk
Classifier: Development Status :: 4 - Beta
Classifier: Intended Audience :: Developers
Classifier: License :: OSI Approved :: MIT License
Classifier: Programming Language :: Python :: 3
Classifier: Programming Language :: Python :: 3.8
Classifier: Programming Language :: Python :: 3.9
Classifier: Programming Language :: Python :: 3.10
Classifier: Programming Language :: Python :: 3.11
Classifier: Programming Language :: Python :: 3.12
Requires-Python: >=3.8
Requires-Dist: pydantic>=2.0.0
Requires-Dist: requests[socks]>=2.31.0
Provides-Extra: dev
Requires-Dist: black>=23.0.0; extra == 'dev'
Requires-Dist: mypy>=1.0.0; extra == 'dev'
Requires-Dist: pytest-cov>=4.0.0; extra == 'dev'
Requires-Dist: pytest>=7.0.0; extra == 'dev'
Requires-Dist: ruff>=0.1.0; extra == 'dev'
Requires-Dist: types-requests>=2.31.0; extra == 'dev'
